symbolicmode/__init__.py
symbolicmode-2.0.1.dist-info/LICENSE
symbolicmode-2.0.1.dist-info/METADATA
symbolicmode-2.0.1.dist-info/WHEEL
symbolicmode-2.0.1.dist-info/top_level.txt
symbolicmode-2.0.1.dist-info/RECORD
