Metadata-Version: 2.1
Name: symbolicmode
Version: 2.0.1
Summary: Code to handle symbolic permissions like GNU chmod does ('a=rx,u+w')
Author-email: Sean Reifschneider <jafo00@gmail.com>
Project-URL: Homepage, https://github.com/linsomniac/symbolicmode
Project-URL: Bug Tracker, https://github.com/linsomniac/symbolicmode/issues
Classifier: Programming Language :: Python :: 3
Classifier: License :: CC0 1.0 Universal (CC0 1.0) Public Domain Dedication
Classifier: Operating System :: OS Independent
Requires-Python: >=3.6
License-File: LICENSE
